inkbot/__init__.py
inkbot/cli.py
inkbot/tasks.py
inkbot-0.0.8.dist-info/LICENSE
inkbot-0.0.8.dist-info/METADATA
inkbot-0.0.8.dist-info/WHEEL
inkbot-0.0.8.dist-info/entry_points.txt
inkbot-0.0.8.dist-info/top_level.txt
inkbot-0.0.8.dist-info/RECORD
